prayikta/Binomialdistribution.py
prayikta/Gaussiandistribution.py
prayikta/Generaldistribution.py
prayikta/__init__.py
prayikta-0.3.dist-info/METADATA
prayikta-0.3.dist-info/WHEEL
prayikta-0.3.dist-info/top_level.txt
prayikta-0.3.dist-info/RECORD
