Metadata-Version: 2.1
Name: prayikta
Version: 0.3
Summary: Gaussian and Binomial distributions
Home-page: UNKNOWN
Author: Manish Soni
Author-email: manish.soni8403@gmail.com
License: UNKNOWN
Platform: UNKNOWN
Classifier: Programming Language :: Python :: 3
Classifier: License :: OSI Approved :: MIT License
Classifier: Operating System :: OS Independent
Requires-Python: >=3.6
